LICENSE
README.md
setup.py
texasholdem/__init__.py
texasholdem/properties.py
texasholdem/sampling.py
texasholdem/texas_collections.py
texasholdem1598.egg-info/PKG-INFO
texasholdem1598.egg-info/SOURCES.txt
texasholdem1598.egg-info/dependency_links.txt
texasholdem1598.egg-info/requires.txt
texasholdem1598.egg-info/top_level.txt